napari_stl_exporter/__init__.py
napari_stl_exporter/_image_to_surface.py
napari_stl_exporter/_reader.py
napari_stl_exporter/_sample_data.py
napari_stl_exporter/_writer.py
napari_stl_exporter/napari.yaml
napari_stl_exporter/_tests/__init__.py
napari_stl_exporter/_tests/test_writer_and_readers.py
napari_stl_exporter/sample_data/Cylinder.tif
napari_stl_exporter/sample_data/Pyramid.tif
napari_stl_exporter/sample_data/__init__.py
napari_stl_exporter/sample_data/pyramid.stl
napari_stl_exporter-0.1.5.dist-info/LICENSE
napari_stl_exporter-0.1.5.dist-info/METADATA
napari_stl_exporter-0.1.5.dist-info/WHEEL
napari_stl_exporter-0.1.5.dist-info/entry_points.txt
napari_stl_exporter-0.1.5.dist-info/top_level.txt
napari_stl_exporter-0.1.5.dist-info/RECORD
