Metadata-Version: 2.1
Name: napari-stl-exporter
Version: 0.1.5
Summary: Exports label images to 3D-printable stl files.
Home-page: https://github.com/jo-mueller/napari-stl-exporter.git
Author: Johannes Soltwedel
Author-email: johannes_richard.soltwedel@tu-dresden.de
License: BSD-3-Clause
Project-URL: Project Site, https://github.com/jo-mueller/napari-stl-exporter
Project-URL: Report Issues, https://github.com/jo-mueller/napari-stl-exporter/issues
Project-URL: Documentation, https://pypi.org/project/napari-stl-exporter/
Project-URL: User Support, https://github.com/jo-mueller/napari-stl-exporter/issues
Project-URL: Twitter, https://twitter.com/jm_mightypirate
Classifier: Development Status :: 3 - Alpha
Classifier: Intended Audience :: Developers
Classifier: Framework :: napari
Classifier: Topic :: Software Development :: Testing
Classifier: Programming Language :: Python
Classifier: Programming Language :: Python :: 3
Classifier: Programming Language :: Python :: 3.7
Classifier: Programming Language :: Python :: 3.8
Classifier: Programming Language :: Python :: 3.9
Classifier: Operating System :: OS Independent
Classifier: License :: OSI Approved :: BSD License
Requires-Python: >=3.7
License-File: LICENSE
Requires-Dist: napari
Requires-Dist: scikit-image
Requires-Dist: vedo (>=2023.4.6)
Requires-Dist: npe2
Requires-Dist: numpy
